[{"type": "system", "content": "Issue created", "timestamp": "2025-04-29T13:25:30.513971", "author": "oswald.bernard@gmail.com"}, {"author": "oswald.bernard@gmail.com", "content": "Coucou", "timestamp": "2025-04-29T13:41:14.125Z", "type": "comment"}, {"name": [{"previous": "first", "new": "first test", "timestamp": "2025-04-29T13:41:50.483Z", "author": "oswald.bernard@gmail.com"}]}, {"pc-function": [{"previous": "Analytics", "new": "PC Valuations", "timestamp": "2025-04-29T14:18:16.112Z", "author": "oswald.bernard@gmail.com"}]}, {"pc-function": [{"previous": "Analytics", "new": "PC Valuations", "timestamp": "2025-04-29T14:18:16.112Z", "author": "oswald.bernard@gmail.com"}], "region": [{"previous": ["Africa"], "new": ["Africa", "Americas"], "timestamp": "2025-04-29T14:18:20.361Z", "author": "oswald.bernard@gmail.com"}]}, {"pc-function": [{"previous": "PC Valuations", "new": "Analytics", "timestamp": "2025-04-29T14:18:29.390Z", "author": "oswald.bernard@gmail.com"}]}, {"type": "system", "content": "Issue submitted", "timestamp": "2025-04-29T14:57:48.058094", "author": "oswald.bernard@gmail.com"}, {"pc-function": [{"previous": "Analytics", "new": "Reporting", "timestamp": "2025-04-29T15:08:04.994Z", "author": "oswald.bernard@gmail.com"}]}]