{"cards": [{"config": {"columns": [{"enablePredefinedFilter": false, "filterOperator": "equals", "filterValue": "", "filterValues": [], "filterable": true, "key": "coucou", "label": "coucou", "options": [], "sortable": true, "type": "text", "visible": true}, {"enablePredefinedFilter": false, "filterOperator": "equals", "filterValue": "", "filterValues": [], "filterable": true, "key": "selectme", "label": "selectme", "options": ["a", "b", "c", "d"], "sortable": true, "type": "select", "visible": true}], "dataSource": "forms-1751987999009", "enableExport": false, "enableSearch": true, "localDBName": "", "pageSize": 25, "pagination": true, "saveToLocalDB": false, "title": ""}, "id": "1752222027268", "size": {"height": "4", "width": 4}, "title": "New datatable", "type": "datatable"}], "createdAt": "2025-07-11T08:19:27.000Z", "description": "Dashboard created automatically", "id": "dashboard-1752221967", "layout": "grid", "name": "Test dev"}